netclam_common/__init__.py
netclam_common/config/__init__.py
netclam_common/config/metric_config.py
netclam_common/database.py
netclam_common/exception.py
netclam_common/models/__init__.py
netclam_common/models/file.py
netclam_common/models/request.py
netclam_common/models/result.py
netclam_common/query.py
netclam_common-0.1.5.dist-info/METADATA
netclam_common-0.1.5.dist-info/WHEEL
netclam_common-0.1.5.dist-info/RECORD
